pysics/__init__.py
pysics/approx.py
pysics/constants.py
pysics/fit.py
pysics/func.py
pysics/objects.py
pysics/plot.py
pysics/prelude.py
pysics/reader.py
pysics/round.py
pysics/statistic.py
pysics/tables.py
pysics/units.py
pysics-0.1.0.dist-info/LICENSE
pysics-0.1.0.dist-info/METADATA
pysics-0.1.0.dist-info/WHEEL
pysics-0.1.0.dist-info/top_level.txt
pysics-0.1.0.dist-info/RECORD
