Metadata-Version: 2.1
Name: pysics
Version: 0.1.0
Summary: Library to make laboratory calculations easy
Author-email: asaltanubes <gustavodragonico@gmail.com>, O2s0k0i3 <elultimopekka@gmail.com>
Project-URL: Repository, https://github.com/asaltanubes/pysics
Project-URL: Issues, https://github.com/asaltanubes/pysics/issues
Keywords: physics,laboratory,units,least squares
Classifier: Intended Audience :: Education
Classifier: Intended Audience :: Science/Research
Requires-Python: >=3.12
License-File: LICENSE
Requires-Dist: numpy >=2.0.1
Requires-Dist: scipy >=1.13.0
Requires-Dist: matplotlib >=3.8.4
Requires-Dist: tabulate >=0.9.0
